blackcortex_cli/__init__.py
blackcortex_cli/main.py
blackcortex_cli/repl.py
blackcortex_cli/config/__init__.py
blackcortex_cli/config/config.py
blackcortex_cli/config/paths.py
blackcortex_cli/core/__init__.py
blackcortex_cli/core/chat_manager.py
blackcortex_cli/core/context.py
blackcortex_cli/core/context_memory.py
blackcortex_cli/core/flag_registry.py
blackcortex_cli/core/log_manager.py
blackcortex_cli/flags/__init__.py
blackcortex_cli/flags/flag_clear_history.py
blackcortex_cli/flags/flag_clear_log.py
blackcortex_cli/flags/flag_clear_memory.py
blackcortex_cli/flags/flag_env.py
blackcortex_cli/flags/flag_log.py
blackcortex_cli/flags/flag_markdown.py
blackcortex_cli/flags/flag_ping.py
blackcortex_cli/flags/flag_set_key.py
blackcortex_cli/flags/flag_stream.py
blackcortex_cli/flags/flag_uninstall.py
blackcortex_cli/flags/flag_update.py
blackcortex_cli/flags/flag_version.py
blackcortex_cli/utils/__init__.py
blackcortex_cli/utils/console.py
blackcortex_cli/utils/formatting.py
blackcortex_cli/utils/metadata.py
blackcortex_gpt_cli-1.3.2.dist-info/licenses/LICENSE
blackcortex_gpt_cli-1.3.2.dist-info/METADATA
blackcortex_gpt_cli-1.3.2.dist-info/WHEEL
blackcortex_gpt_cli-1.3.2.dist-info/entry_points.txt
blackcortex_gpt_cli-1.3.2.dist-info/top_level.txt
blackcortex_gpt_cli-1.3.2.dist-info/RECORD
