Metadata-Version: 2.4
Name: blackcortex-gpt-cli
Version: 1.3.2
Summary: Terminal-based GPT CLI with memory, markdown, and stream support
Author-email: Konijima <konijima@blackcortex.net>
License-Expression: MIT
Keywords: gpt,cli,terminal,openai
Classifier: Programming Language :: Python :: 3
Classifier: Environment :: Console
Classifier: Intended Audience :: Developers
Classifier: Topic :: Software Development :: Libraries :: Python Modules
Requires-Python: >=3.8
License-File: LICENSE
Requires-Dist: openai
Requires-Dist: rich
Requires-Dist: tiktoken
Requires-Dist: prompt_toolkit
Requires-Dist: python-dotenv
Provides-Extra: dev
Requires-Dist: build; extra == "dev"
Requires-Dist: pre-commit; extra == "dev"
Requires-Dist: pylint; extra == "dev"
Requires-Dist: pytest; extra == "dev"
Requires-Dist: pytest-cov; extra == "dev"
Requires-Dist: pytest-testdox; extra == "dev"
Requires-Dist: ruff; extra == "dev"
Requires-Dist: setuptools; extra == "dev"
Requires-Dist: twine; extra == "dev"
Requires-Dist: wheel; extra == "dev"
Dynamic: license-file
